{
  "id": "90f3f5e4-c157-4dd0-9f0e-b9742faef0db",
  "prevId": "00000000-0000-0000-0000-000000000000",
  "version": "7",
  "dialect": "postgresql",
  "tables": {
    "public.categories": {
      "name": "categories",
      "schema": "",
      "columns": {
        "id": {
          "name": "id",
          "type": "serial",
          "primaryKey": true,
          "notNull": true
        },
        "shop_id": {
          "name": "shop_id",
          "type": "integer",
          "primaryKey": false,
          "notNull": true
        },
        "name": {
          "name": "name",
          "type": "text",
          "primaryKey": false,
          "notNull": true
        },
        "slug": {
          "name": "slug",
          "type": "text",
          "primaryKey": false,
          "notNull": true
        }
      },
      "indexes": {},
      "foreignKeys": {
        "categories_shop_id_shops_id_fk": {
          "name": "categories_shop_id_shops_id_fk",
          "tableFrom": "categories",
          "tableTo": "shops",
          "columnsFrom": [
            "shop_id"
          ],
          "columnsTo": [
            "id"
          ],
          "onDelete": "cascade",
          "onUpdate": "no action"
        }
      },
      "compositePrimaryKeys": {},
      "uniqueConstraints": {},
      "policies": {},
      "checkConstraints": {},
      "isRLSEnabled": false
    },
    "public.order_items": {
      "name": "order_items",
      "schema": "",
      "columns": {
        "id": {
          "name": "id",
          "type": "serial",
          "primaryKey": true,
          "notNull": true
        },
        "order_id": {
          "name": "order_id",
          "type": "integer",
          "primaryKey": false,
          "notNull": true
        },
        "product_id": {
          "name": "product_id",
          "type": "integer",
          "primaryKey": false,
          "notNull": true
        },
        "quantity": {
          "name": "quantity",
          "type": "integer",
          "primaryKey": false,
          "notNull": true
        },
        "price_at_time": {
          "name": "price_at_time",
          "type": "integer",
          "primaryKey": false,
          "notNull": true
        }
      },
      "indexes": {},
      "foreignKeys": {
        "order_items_order_id_orders_id_fk": {
          "name": "order_items_order_id_orders_id_fk",
          "tableFrom": "order_items",
          "tableTo": "orders",
          "columnsFrom": [
            "order_id"
          ],
          "columnsTo": [
            "id"
          ],
          "onDelete": "cascade",
          "onUpdate": "no action"
        },
        "order_items_product_id_products_id_fk": {
          "name": "order_items_product_id_products_id_fk",
          "tableFrom": "order_items",
          "tableTo": "products",
          "columnsFrom": [
            "product_id"
          ],
          "columnsTo": [
            "id"
          ],
          "onDelete": "cascade",
          "onUpdate": "no action"
        }
      },
      "compositePrimaryKeys": {},
      "uniqueConstraints": {},
      "policies": {},
      "checkConstraints": {},
      "isRLSEnabled": false
    },
    "public.orders": {
      "name": "orders",
      "schema": "",
      "columns": {
        "id": {
          "name": "id",
          "type": "serial",
          "primaryKey": true,
          "notNull": true
        },
        "shop_id": {
          "name": "shop_id",
          "type": "integer",
          "primaryKey": false,
          "notNull": true
        },
        "customer_name": {
          "name": "customer_name",
          "type": "text",
          "primaryKey": false,
          "notNull": true
        },
        "customer_email": {
          "name": "customer_email",
          "type": "text",
          "primaryKey": false,
          "notNull": true
        },
        "customer_phone": {
          "name": "customer_phone",
          "type": "text",
          "primaryKey": false,
          "notNull": false
        },
        "shipping_address": {
          "name": "shipping_address",
          "type": "jsonb",
          "primaryKey": false,
          "notNull": false
        },
        "tracking_code": {
          "name": "tracking_code",
          "type": "text",
          "primaryKey": false,
          "notNull": false
        },
        "total_amount": {
          "name": "total_amount",
          "type": "integer",
          "primaryKey": false,
          "notNull": true
        },
        "status": {
          "name": "status",
          "type": "text",
          "primaryKey": false,
          "notNull": false,
          "default": "'pending'"
        },
        "created_at": {
          "name": "created_at",
          "type": "timestamp",
          "primaryKey": false,
          "notNull": true,
          "default": "now()"
        }
      },
      "indexes": {},
      "foreignKeys": {
        "orders_shop_id_shops_id_fk": {
          "name": "orders_shop_id_shops_id_fk",
          "tableFrom": "orders",
          "tableTo": "shops",
          "columnsFrom": [
            "shop_id"
          ],
          "columnsTo": [
            "id"
          ],
          "onDelete": "cascade",
          "onUpdate": "no action"
        }
      },
      "compositePrimaryKeys": {},
      "uniqueConstraints": {},
      "policies": {},
      "checkConstraints": {},
      "isRLSEnabled": false
    },
    "public.products": {
      "name": "products",
      "schema": "",
      "columns": {
        "id": {
          "name": "id",
          "type": "serial",
          "primaryKey": true,
          "notNull": true
        },
        "shop_id": {
          "name": "shop_id",
          "type": "integer",
          "primaryKey": false,
          "notNull": true
        },
        "category_id": {
          "name": "category_id",
          "type": "integer",
          "primaryKey": false,
          "notNull": false
        },
        "name": {
          "name": "name",
          "type": "text",
          "primaryKey": false,
          "notNull": true
        },
        "description": {
          "name": "description",
          "type": "text",
          "primaryKey": false,
          "notNull": false
        },
        "price": {
          "name": "price",
          "type": "integer",
          "primaryKey": false,
          "notNull": true
        },
        "stock": {
          "name": "stock",
          "type": "integer",
          "primaryKey": false,
          "notNull": false,
          "default": 0
        },
        "image_url": {
          "name": "image_url",
          "type": "text",
          "primaryKey": false,
          "notNull": false
        },
        "images": {
          "name": "images",
          "type": "jsonb",
          "primaryKey": false,
          "notNull": false,
          "default": "'[]'::jsonb"
        },
        "created_at": {
          "name": "created_at",
          "type": "timestamp",
          "primaryKey": false,
          "notNull": true,
          "default": "now()"
        }
      },
      "indexes": {},
      "foreignKeys": {
        "products_shop_id_shops_id_fk": {
          "name": "products_shop_id_shops_id_fk",
          "tableFrom": "products",
          "tableTo": "shops",
          "columnsFrom": [
            "shop_id"
          ],
          "columnsTo": [
            "id"
          ],
          "onDelete": "cascade",
          "onUpdate": "no action"
        },
        "products_category_id_categories_id_fk": {
          "name": "products_category_id_categories_id_fk",
          "tableFrom": "products",
          "tableTo": "categories",
          "columnsFrom": [
            "category_id"
          ],
          "columnsTo": [
            "id"
          ],
          "onDelete": "set null",
          "onUpdate": "no action"
        }
      },
      "compositePrimaryKeys": {},
      "uniqueConstraints": {},
      "policies": {},
      "checkConstraints": {},
      "isRLSEnabled": false
    },
    "public.shop_settings": {
      "name": "shop_settings",
      "schema": "",
      "columns": {
        "id": {
          "name": "id",
          "type": "serial",
          "primaryKey": true,
          "notNull": true
        },
        "shop_id": {
          "name": "shop_id",
          "type": "integer",
          "primaryKey": false,
          "notNull": true
        },
        "mp_access_token": {
          "name": "mp_access_token",
          "type": "text",
          "primaryKey": false,
          "notNull": false
        },
        "mp_public_key": {
          "name": "mp_public_key",
          "type": "text",
          "primaryKey": false,
          "notNull": false
        },
        "is_active": {
          "name": "is_active",
          "type": "boolean",
          "primaryKey": false,
          "notNull": false,
          "default": true
        },
        "created_at": {
          "name": "created_at",
          "type": "timestamp",
          "primaryKey": false,
          "notNull": true,
          "default": "now()"
        }
      },
      "indexes": {},
      "foreignKeys": {
        "shop_settings_shop_id_shops_id_fk": {
          "name": "shop_settings_shop_id_shops_id_fk",
          "tableFrom": "shop_settings",
          "tableTo": "shops",
          "columnsFrom": [
            "shop_id"
          ],
          "columnsTo": [
            "id"
          ],
          "onDelete": "cascade",
          "onUpdate": "no action"
        }
      },
      "compositePrimaryKeys": {},
      "uniqueConstraints": {
        "shop_settings_shop_id_unique": {
          "name": "shop_settings_shop_id_unique",
          "nullsNotDistinct": false,
          "columns": [
            "shop_id"
          ]
        }
      },
      "policies": {},
      "checkConstraints": {},
      "isRLSEnabled": false
    },
    "public.shops": {
      "name": "shops",
      "schema": "",
      "columns": {
        "id": {
          "name": "id",
          "type": "serial",
          "primaryKey": true,
          "notNull": true
        },
        "owner_id": {
          "name": "owner_id",
          "type": "text",
          "primaryKey": false,
          "notNull": true
        },
        "name": {
          "name": "name",
          "type": "text",
          "primaryKey": false,
          "notNull": true
        },
        "slug": {
          "name": "slug",
          "type": "text",
          "primaryKey": false,
          "notNull": true
        },
        "plan": {
          "name": "plan",
          "type": "text",
          "primaryKey": false,
          "notNull": false,
          "default": "'free'"
        },
        "created_at": {
          "name": "created_at",
          "type": "timestamp",
          "primaryKey": false,
          "notNull": true,
          "default": "now()"
        }
      },
      "indexes": {},
      "foreignKeys": {},
      "compositePrimaryKeys": {},
      "uniqueConstraints": {
        "shops_slug_unique": {
          "name": "shops_slug_unique",
          "nullsNotDistinct": false,
          "columns": [
            "slug"
          ]
        }
      },
      "policies": {},
      "checkConstraints": {},
      "isRLSEnabled": false
    }
  },
  "enums": {},
  "schemas": {},
  "sequences": {},
  "roles": {},
  "policies": {},
  "views": {},
  "_meta": {
    "columns": {},
    "schemas": {},
    "tables": {}
  }
}